Metadata-Version: 2.1
Name: calfem-python-small
Version: 3.6.5
Summary: CALFEM for Python
Home-page: https://github.com/CALFEM/calfem-python
Author: Jonas Lindemann, et al
Author-email: jonas.lindemann@lunarc.lu.se
License: MIT
Keywords: finite element,math,numerics
Classifier: Development Status :: 4 - Beta
Classifier: Intended Audience :: Developers
Classifier: Topic :: Software Development :: Build Tools
Classifier: License :: OSI Approved :: MIT License
Classifier: Programming Language :: Python :: 3
Classifier: Programming Language :: Python :: 3.7
Classifier: Programming Language :: Python :: 3.8
Classifier: Programming Language :: Python :: 3.9
Classifier: Programming Language :: Python :: 3.10
Classifier: Programming Language :: Python :: 3.11
Classifier: Programming Language :: Python :: 3.12
License-File: LICENSE
License-File: LICENSE.txt
Requires-Dist: numpy
Requires-Dist: visvis
Requires-Dist: matplotlib
Requires-Dist: scipy
Requires-Dist: gmsh
Requires-Dist: tabulate
